qstylizer/__init__.py
qstylizer/parser.py
qstylizer/style.py
qstylizer/descriptor/__init__.py
qstylizer/descriptor/prop.py
qstylizer/descriptor/pseudoprop.py
qstylizer/descriptor/pseudostate.py
qstylizer/descriptor/qclass.py
qstylizer/descriptor/stylerule.py
qstylizer/descriptor/subcontrol.py
qstylizer-0.2.4.dist-info/LICENSE.txt
qstylizer-0.2.4.dist-info/METADATA
qstylizer-0.2.4.dist-info/WHEEL
qstylizer-0.2.4.dist-info/pbr.json
qstylizer-0.2.4.dist-info/top_level.txt
qstylizer-0.2.4.dist-info/RECORD
