Metadata-Version: 2.1
Name: qstylizer
Version: 0.2.4
Summary: Stylesheet Generator for PyQt{4-5}/PySide{1-2}
Home-page: https://github.com/blambright/qstylizer
Author: Brett Lambright
License: MIT
Platform: UNKNOWN
Classifier: Development Status :: 4 - Beta
Classifier: License :: OSI Approved :: MIT License
Classifier: Intended Audience :: Developers
Classifier: Operating System :: OS Independent
Classifier: Programming Language :: Python
Classifier: Environment :: X11 Applications :: Qt
Classifier: Programming Language :: Python :: 2
Classifier: Programming Language :: Python :: 2.7
Classifier: Programming Language :: Python :: 3
Classifier: Programming Language :: Python :: 3.5
Classifier: Programming Language :: Python :: 3.7
Classifier: Programming Language :: Python :: 3.9
Provides-Extra: doc
Provides-Extra: test
Provides-Extra: test27
License-File: LICENSE.txt
